{
  "resourceType" : "Location",
  "id" : "NavalMedicalResearchUnit",
  "text" : {
    "status" : "generated",
    "div" : "<div xmlns=\"http://www.w3.org/1999/xhtml\"><p class=\"res-header-id\"><b>Generated Narrative: Location NavalMedicalResearchUnit</b></p><a name=\"NavalMedicalResearchUnit\"> </a><a name=\"hcNavalMedicalResearchUnit\"> </a><a name=\"NavalMedicalResearchUnit-en-US\"> </a><p><b>name</b>: Naval Medical Research Unit Dayton</p><p><b>description</b>: Navy diving medicine research and hyperbaric treatment</p><p><b>address</b>: Dayton OH US </p></div>"
  },
  "name" : "Naval Medical Research Unit Dayton",
  "description" : "Navy diving medicine research and hyperbaric treatment",
  "address" : {
    "city" : "Dayton",
    "state" : "OH",
    "country" : "US"
  }
}